adafruit_circuitpython_pyportal-7.1.2.dist-info/licenses/LICENSE
adafruit_pyportal/__init__.py
adafruit_pyportal/graphics.py
adafruit_pyportal/network.py
adafruit_pyportal/peripherals.py
adafruit_circuitpython_pyportal-7.1.2.dist-info/METADATA
adafruit_circuitpython_pyportal-7.1.2.dist-info/WHEEL
adafruit_circuitpython_pyportal-7.1.2.dist-info/top_level.txt
adafruit_circuitpython_pyportal-7.1.2.dist-info/RECORD
