Metadata-Version: 2.4
Name: adafruit-circuitpython-pyportal
Version: 7.1.2
Summary: CircuitPython driver for Adafruit PyPortal
Author-email: Adafruit Industries <circuitpython@adafruit.com>
License: MIT
Project-URL: Homepage, https://github.com/adafruit/Adafruit_CircuitPython_REPLACE
Keywords: adafruit,pyportal,display,iot,wifi,hardware,micropythoncircuitpython
Classifier: Intended Audience :: Developers
Classifier: Topic :: Software Development :: Libraries
Classifier: Topic :: Software Development :: Embedded Systems
Classifier: Topic :: System :: Hardware
Classifier: License :: OSI Approved :: MIT License
Classifier: Programming Language :: Python :: 3
License-File: LICENSE
Requires-Dist: Adafruit-Blinka-displayio
Requires-Dist: Adafruit-Blinka
Requires-Dist: adafruit-circuitpython-bitmap-font
Requires-Dist: adafruit-circuitpython-busdevice
Requires-Dist: adafruit-circuitpython-touchscreen
Requires-Dist: adafruit-circuitpython-esp32spi
Requires-Dist: adafruit-circuitpython-requests
Requires-Dist: adafruit-circuitpython-neopixel
Requires-Dist: adafruit-circuitpython-portalbase
Provides-Extra: optional
Dynamic: license-file
